{
	"site-title": "My Blog",
	"site-tagline": "I write about things other people only dream about",
	"widget-image": "https://fillmurray.com/600/600",
	"new-widget": [
		{
			"widget-header": "Widget Header",
			"widget-text": "Lorem ipsum dolor sit amet consectetur adipisicing elit. Delectus rerum libero enim commodi expedita molestiae, modi veniam at vero est!"
		}
	],
	"new-post": [
		{
			"post-title": "New Post Title",
			"post-text": "Lorem ipsum dolor sit amet, consectetur adipiscing elit. Cras dolor justo, lobortis eget felis eget, sodales semper odio. In vel vulputate dui, a suscipit nunc. Nunc quam lacus, fermentum vel urna nec, fermentum tristique ex. Etiam interdum ante mi, vitae viverra velit pretium sit amet. Quisque et nunc diam. Suspendisse id magna id ligula pharetra laoreet. Suspendisse accumsan cursus tortor at pulvinar. Curabitur laoreet scelerisque nisi eu pellentesque. Nunc non mattis erat. Fusce fringilla commodo ipsum sit amet viverra. Sed quis arcu dignissim, euismod lacus non, maximus augue. Nunc lacus felis, cursus id mauris ac, egestas sodales lorem. Proin quam sem, fermentum quis elementum vel, posuere eget erat.\n\nCurabitur sodales cursus arcu ut elementum. Class aptent taciti sociosqu ad litora torquent per conubia nostra, per inceptos himenaeos. Ut vestibulum lacus vel leo pretium, in fringilla quam rutrum. Cras malesuada volutpat tortor, tincidunt fermentum odio dignissim at. Interdum et malesuada fames ac ante ipsum primis in faucibus. Vivamus dui tellus, scelerisque nec ipsum ut, blandit malesuada lectus. Vestibulum sodales, risus nec pretium egestas, orci nunc pretium turpis, eu ultricies elit magna ut risus.\n\nCurabitur sodales cursus arcu ut elementum. Class aptent taciti sociosqu ad litora torquent per conubia nostra, per inceptos himenaeos. Ut vestibulum lacus vel leo pretium, in fringilla quam rutrum. Cras malesuada volutpat tortor, tincidunt fermentum odio dignissim at. Interdum et malesuada fames ac ante ipsum primis in faucibus. Vivamus dui tellus, scelerisque nec ipsum ut, blandit malesuada lectus. Vestibulum sodales, risus nec pretium egestas, orci nunc pretium turpis, eu ultricies elit magna ut risus. Proin quam sem, fermentum quis elementum vel, posuere eget erat.\n\nCurabitur sodales cursus arcu ut elementum. Class aptent taciti sociosqu ad litora torquent per conubia nostra, per inceptos himenaeos. Ut vestibulum lacus vel leo pretium, in fringilla quam rutrum. Cras malesuada volutpat tortor, tincidunt fermentum odio dignissim at. Interdum et malesuada fames ac ante ipsum primis in faucibus. Vivamus dui tellus, scelerisque nec ipsum ut, blandit malesuada lectus. Vestibulum sodales, risus nec pretium egestas, orci nunc pretium turpis, eu ultricies elit magna ut risus."
		}
	]
}